airsenal/__init__.py
airsenal/conftest.py
airsenal/scratch
airsenal/scratch~
airsenal/api/app.py
airsenal/api/exceptions.py
airsenal/api/session_example.py
airsenal/data/FPL_1718.json
airsenal/data/FPL_1819.json
airsenal/data/FPL_1920.json
airsenal/data/FPL_2021.json
airsenal/data/FPL_2122.json
airsenal/data/FPL_2223.json
airsenal/data/FPL_2324.json
airsenal/data/FPL_2425.json
airsenal/data/FPL_LOGIN_AIrsenal
airsenal/data/FPL_LOGIN_Nick
airsenal/data/FPL_PASSWORD_AIrsenal
airsenal/data/FPL_PASSWORD_Nick
airsenal/data/FPL_TEAM_ID_Nick
airsenal/data/FPL_TEAM_ID~
airsenal/data/Replay_2122_GW1_GW38_202210071157.json
airsenal/data/absences_1516.csv
airsenal/data/absences_1617.csv
airsenal/data/absences_1718.csv
airsenal/data/absences_1819.csv
airsenal/data/absences_1920.csv
airsenal/data/absences_2021.csv
airsenal/data/absences_2122.csv
airsenal/data/absences_2223.csv
airsenal/data/absences_2324.csv
airsenal/data/absences_2425.csv
airsenal/data/airsenal_gw_2021.json
airsenal/data/airsenal_gw_2122.json
airsenal/data/airsenal_gw_2223.json
airsenal/data/airsenal_gw_2324.json
airsenal/data/airsenal_gw_2425.json
airsenal/data/airsenal_history_2021.json
airsenal/data/airsenal_history_2122.json
airsenal/data/airsenal_history_2223.json
airsenal/data/airsenal_history_2324.json
airsenal/data/airsenal_history_2425.json
airsenal/data/airsenal_transfer_2021.json
airsenal/data/airsenal_transfer_2122.json
airsenal/data/airsenal_transfer_2223.json
airsenal/data/airsenal_transfer_2324.json
airsenal/data/airsenal_transfer_2425.json
airsenal/data/alternative_player_names.csv
airsenal/data/alternative_player_names.json
airsenal/data/data_2223.db
airsenal/data/duplicate_player_names.csv
airsenal/data/fifa_team_ratings.csv
airsenal/data/fifa_team_ratings_1718.csv
airsenal/data/fifa_team_ratings_1819.csv
airsenal/data/fifa_team_ratings_1920.csv
airsenal/data/fifa_team_ratings_2021.csv
airsenal/data/fifa_team_ratings_2122.csv
airsenal/data/fifa_team_ratings_2223.csv
airsenal-1.11.0.dist-info/METADATA
airsenal-1.11.0.dist-info/WHEEL
airsenal-1.11.0.dist-info/entry_points.txt
airsenal-1.11.0.dist-info/licenses/LICENSE
airsenal-1.11.0.dist-info/RECORD
