Metadata-Version: 2.4
Name: airsenal
Version: 1.11.0
Summary: AI manager for Fantasy Premier League
Author-email: Angus Williams <anguswilliams91@gmail.com>, Jack Roberts <jroberts@turing.ac.uk>, Nick Barlow <nbarlow@turing.ac.uk>
License: MIT License
License-File: LICENSE
Requires-Python: >=3.10
Requires-Dist: beautifulsoup4>=4.12.3
Requires-Dist: bpl-next>=0.4.0
Requires-Dist: click>=8.1.7
Requires-Dist: dateparser>=1.2.0
Requires-Dist: deap>=1.4.1
Requires-Dist: html5lib>=1.1
Requires-Dist: jax==0.4.24
Requires-Dist: jaxlib==0.4.24
Requires-Dist: lxml>=5.1.0
Requires-Dist: numpy<2,>1
Requires-Dist: pandas>=2.2.1
Requires-Dist: platformdirs>=4.2.0
Requires-Dist: prettytable>=3.10.0
Requires-Dist: python-dateutil>=2.8.2
Requires-Dist: requests>=2.31.0
Requires-Dist: sqlalchemy>=2.0.27
Requires-Dist: tqdm>=4.66.2
Provides-Extra: api
Requires-Dist: flask>=3.0.2; extra == 'api'
Provides-Extra: dev
Requires-Dist: mypy>=1.17.0; extra == 'dev'
Requires-Dist: pre-commit>=3.6.2; extra == 'dev'
Requires-Dist: pytest-cov>=4.1.0; extra == 'dev'
Requires-Dist: pytest-sugar>=1.0.0; extra == 'dev'
Requires-Dist: pytest>=8.0.1; extra == 'dev'
Requires-Dist: ruff>=0.6.0; extra == 'dev'
Requires-Dist: types-dateparser>=1.2.2.20250627; extra == 'dev'
Requires-Dist: types-python-dateutil>=2.9.0.20250708; extra == 'dev'
Requires-Dist: types-requests>=2.32.4.20250611; extra == 'dev'
Provides-Extra: notebook
Requires-Dist: jupyterlab>=4.1.2; extra == 'notebook'
Provides-Extra: plot
Requires-Dist: matplotlib>=3.8.3; extra == 'plot'
Requires-Dist: seaborn>=0.13.2; extra == 'plot'
